leafwaxtools/__init__.py
leafwaxtools/api/__init__.py
leafwaxtools/api/chain.py
leafwaxtools/api/isotope.py
leafwaxtools/data/__init__.py
leafwaxtools/tests/__init__.py
leafwaxtools/tests/test_api_Chain.py
leafwaxtools/tests/test_api_Isotope.py
leafwaxtools/utils/__init__.py
leafwaxtools/utils/data_type_enum.py
leafwaxtools/utils/validate_data.py
leafwaxtools-2.0.0.dist-info/METADATA
leafwaxtools-2.0.0.dist-info/WHEEL
leafwaxtools-2.0.0.dist-info/top_level.txt
leafwaxtools-2.0.0.dist-info/RECORD
