Metadata-Version: 2.4
Name: leafwaxtools
Version: 2.0.0
Summary: A package for calculating common indices from plant leaf wax carbon chain-length distribution and isotopic data
Author-email: Kurt Lindberg <kurtrlindberg@gmail.com>
License: Apache-2.0
Project-URL: Homepage, https://github.com/kurtlindberg/leafwaxtools
Project-URL: Issues, https://github.com/kurtrlindberg/leafwaxtools/issues
Requires-Python: >=3.12
Requires-Dist: pandas
Requires-Dist: numpy
Requires-Dist: scikit-learn
Requires-Dist: scipy
Requires-Dist: composition_stats
